dbr_test_pckg/__init__.py
dbr_test_pckg/__main__.py
dbr_test_pckg/show.py
dbr_test_pckg-1.2.0.dist-info/licenses/LICENSE.txt
dbr_test_pckg-1.2.0.dist-info/METADATA
dbr_test_pckg-1.2.0.dist-info/WHEEL
dbr_test_pckg-1.2.0.dist-info/entry_points.txt
dbr_test_pckg-1.2.0.dist-info/top_level.txt
dbr_test_pckg-1.2.0.dist-info/RECORD
