Metadata-Version: 2.4
Name: dbr_test_pckg
Version: 1.2.0
Summary: My test package!
Author-email: Dominik Brzoň <brzon.dominik@gmail.com>
Maintainer-email: Dominik Brzoň <brzon.dominik@gmail.com>
License: Copyright (C) <date> <copyright holders>
Project-URL: Homepage, https://github.com/mbrzon/milan_brzon
Project-URL: Documentation, https://github.com/mbrzon/milan_brzon/README.md
Keywords: Brzon
Classifier: Programming Language :: Python :: 3.9
Classifier: Programming Language :: Python :: Implementation :: CPython
Classifier: License :: OSI Approved :: BSD License
Classifier: Intended Audience :: Developers
Classifier: Operating System :: POSIX :: Linux
Classifier: Operating System :: Microsoft :: Windows
Classifier: Operating System :: MacOS
Classifier: Operating System :: MacOS :: MacOS X
Requires-Python: >=3.9
License-File: LICENSE.txt
Dynamic: license-file
